<?xml version="1.0"?>
<iwxxm:METAR xmlns:aixm="http://www.aixm.aero/schema/5.1.1" xmlns:iwxxm="http://icao.int/iwxxm/3.0" xmlns:gml="http://www.opengis.net/gml/3.2" xmlns:xlink="http://www.w3.org/1999/xlink" xmlns:xsi="http://www.w3.org/2001/XMLSchema-instance" xsi:schemaLocation="http://icao.int/iwxxm/3.0 http://schemas.wmo.int/iwxxm/3.0/iwxxm.xsd" reportStatus="NORMAL" automatedStation="false" permissibleUsage="OPERATIONAL" translationCentreName="NCEP Central Operations" translationCentreDesignator="KWNO" translationTime="2020-05-26T12:26:40Z" translatedBulletinReceptionTime="2020-05-26T12:26:40Z" translatedBulletinID="SAXX99XXXX260000" gml:id="uuid.618aa8bd-898b-46a5-9ef5-f0d04da5d908">
  <iwxxm:issueTime>
    <gml:TimeInstant gml:id="uuid.3b4f3885-d168-417c-809b-0d3b6e4de9e5">
      <gml:timePosition>2020-04-29T00:00:00Z</gml:timePosition>
    </gml:TimeInstant>
  </iwxxm:issueTime>
  <iwxxm:aerodrome>
    <aixm:AirportHeliport gml:id="uuid.c6fc9f40-8b72-4d22-8fe6-3f5ca14fa3bb">
      <aixm:timeSlice>
        <aixm:AirportHeliportTimeSlice gml:id="uuid.8346900f-aec4-4c90-9b4c-6046a6328602">
          <gml:validTime/>
          <aixm:interpretation>SNAPSHOT</aixm:interpretation>
          <aixm:designator>UIBB</aixm:designator>
          <aixm:name>BRATSK/IRKUTSK</aixm:name>
          <aixm:locationIndicatorICAO>UIBB</aixm:locationIndicatorICAO>
          <aixm:ARP>
            <aixm:ElevatedPoint srsDimension="2" srsName="http://www.opengis.net/def/crs/EPSG/0/4326" axisLabels="Lat Long" gml:id="uuid.36ba3e1b-c369-48da-9d8e-4650edbd62fa">
              <gml:pos>56.37 101.7</gml:pos>
              <aixm:elevation uom="M">490</aixm:elevation>
              <aixm:verticalDatum>EGM_96</aixm:verticalDatum>
            </aixm:ElevatedPoint>
          </aixm:ARP>
        </aixm:AirportHeliportTimeSlice>
      </aixm:timeSlice>
    </aixm:AirportHeliport>
  </iwxxm:aerodrome>
  <iwxxm:observationTime xlink:href="#uuid.3b4f3885-d168-417c-809b-0d3b6e4de9e5"/>
  <iwxxm:observation>
    <iwxxm:MeteorologicalAerodromeObservation gml:id="uuid.781ec16f-b053-4b26-858d-5fb5b1af48b0" cloudAndVisibilityOK="false">
      <iwxxm:airTemperature uom="Cel">-1</iwxxm:airTemperature>
      <iwxxm:dewpointTemperature uom="Cel">-7</iwxxm:dewpointTemperature>
      <iwxxm:qnh uom="hPa">1018</iwxxm:qnh>
      <iwxxm:surfaceWind>
        <iwxxm:AerodromeSurfaceWind variableWindDirection="true">
          <iwxxm:meanWindDirection uom="deg">250</iwxxm:meanWindDirection>
          <iwxxm:meanWindSpeed uom="m/s">5</iwxxm:meanWindSpeed>
          <iwxxm:extremeClockwiseWindDirection uom="deg">280</iwxxm:extremeClockwiseWindDirection>
          <iwxxm:extremeCounterClockwiseWindDirection uom="deg">220</iwxxm:extremeCounterClockwiseWindDirection>
        </iwxxm:AerodromeSurfaceWind>
      </iwxxm:surfaceWind>
      <iwxxm:visibility>
        <iwxxm:AerodromeHorizontalVisibility>
          <iwxxm:prevailingVisibility uom="m">10000</iwxxm:prevailingVisibility>
          <iwxxm:prevailingVisibilityOperator>ABOVE</iwxxm:prevailingVisibilityOperator>
        </iwxxm:AerodromeHorizontalVisibility>
      </iwxxm:visibility>
      <iwxxm:cloud>
        <iwxxm:AerodromeCloud>
          <iwxxm:layer>
            <iwxxm:CloudLayer>
              <iwxxm:amount xlink:href="http://codes.wmo.int/49-2/CloudAmountReportedAtAerodrome/SCT"/>
              <iwxxm:base uom="[ft_i]">3300</iwxxm:base>
            </iwxxm:CloudLayer>
          </iwxxm:layer>
        </iwxxm:AerodromeCloud>
      </iwxxm:cloud>
      <iwxxm:runwayState>
        <iwxxm:AerodromeRunwayState allRunways="false">
          <iwxxm:runway>
            <aixm:RunwayDirection gml:id="uuid.95785fc2-07f5-4211-af9c-fa9864a5627d">
              <aixm:timeSlice>
                <aixm:RunwayDirectionTimeSlice gml:id="uuid.c4e45e2e-8ff7-429e-8cc5-a8cf4856d732">
                  <gml:validTime/>
                  <aixm:interpretation>SNAPSHOT</aixm:interpretation>
                  <aixm:designator>30</aixm:designator>
                </aixm:RunwayDirectionTimeSlice>
              </aixm:timeSlice>
            </aixm:RunwayDirection>
          </iwxxm:runway>
          <iwxxm:depositType xlink:href="http://codes.wmo.int/bufr4/codeflag/0-20-086/8"/>
          <iwxxm:contamination xlink:href="http://codes.wmo.int/bufr4/codeflag/0-20-087/1"/>
          <iwxxm:depthOfDeposit uom="mm">10</iwxxm:depthOfDeposit>
          <iwxxm:estimatedSurfaceFrictionOrBrakingAction xlink:href="http://codes.wmo.int/bufr4/codeflag/0-20-089/50"/>
        </iwxxm:AerodromeRunwayState>
      </iwxxm:runwayState>
    </iwxxm:MeteorologicalAerodromeObservation>
  </iwxxm:observation>
  <iwxxm:trendForecast xsi:nil="true" nilReason="http://codes.wmo.int/common/nil/noSignificantChange"/>
</iwxxm:METAR>
