<?xml version="1.0"?>
<iwxxm:SPECI xmlns:aixm="http://www.aixm.aero/schema/5.1.1" xmlns:iwxxm="http://icao.int/iwxxm/2023-1" xmlns:gml="http://www.opengis.net/gml/3.2" xmlns:xlink="http://www.w3.org/1999/xlink" xmlns:xsi="http://www.w3.org/2001/XMLSchema-instance" xsi:schemaLocation="http://icao.int/iwxxm/2023-1 https://schemas.wmo.int/iwxxm/2023-1/iwxxm.xsd" reportStatus="NORMAL" automatedStation="false" permissibleUsage="OPERATIONAL" gml:id="uuid.f0c18132-4a06-44e8-b8d4-34f11b810035">
  <iwxxm:issueTime>
    <gml:TimeInstant gml:id="uuid.04b9127a-1dff-4369-bab1-5f2594fa8031">
      <gml:timePosition>2023-05-29T00:20:00Z</gml:timePosition>
    </gml:TimeInstant>
  </iwxxm:issueTime>
  <iwxxm:aerodrome>
    <aixm:AirportHeliport gml:id="uuid.3b2454a7-b88e-408b-9521-32e540fa2f81">
      <aixm:timeSlice>
        <aixm:AirportHeliportTimeSlice gml:id="uuid.d758c315-eace-4abe-ab61-56dd0cd66fb9">
          <gml:validTime/>
          <aixm:interpretation>SNAPSHOT</aixm:interpretation>
          <aixm:name>MALMO STURUP AIRPORT</aixm:name>
          <aixm:locationIndicatorICAO>ESMS</aixm:locationIndicatorICAO>
          <aixm:designatorIATA>MMX</aixm:designatorIATA>
          <aixm:ARP>
            <aixm:ElevatedPoint srsDimension="2" srsName="http://www.opengis.net/def/crs/EPSG/0/4326" axisLabels="Lat Long" gml:id="uuid.462dd3b8-bdc1-436f-bc62-39a6cc6d7836">
              <gml:pos>55.53630536 13.37619781</gml:pos>
              <aixm:elevation uom="M">72</aixm:elevation>
              <aixm:verticalDatum>EGM_96</aixm:verticalDatum>
            </aixm:ElevatedPoint>
          </aixm:ARP>
        </aixm:AirportHeliportTimeSlice>
      </aixm:timeSlice>
    </aixm:AirportHeliport>
  </iwxxm:aerodrome>
  <iwxxm:observationTime xlink:href="#uuid.04b9127a-1dff-4369-bab1-5f2594fa8031"/>
  <iwxxm:observation>
    <iwxxm:MeteorologicalAerodromeObservation gml:id="uuid.bbab97ab-1e83-41bc-b9b6-aeb8f1fafb40" cloudAndVisibilityOK="true">
      <iwxxm:airTemperature uom="Cel">1</iwxxm:airTemperature>
      <iwxxm:dewpointTemperature uom="Cel">-3</iwxxm:dewpointTemperature>
      <iwxxm:qnh uom="hPa">1004</iwxxm:qnh>
      <iwxxm:surfaceWind>
        <iwxxm:AerodromeSurfaceWind variableWindDirection="false">
          <iwxxm:meanWindDirection uom="deg">90</iwxxm:meanWindDirection>
          <iwxxm:meanWindSpeed uom="[kn_i]">22</iwxxm:meanWindSpeed>
        </iwxxm:AerodromeSurfaceWind>
      </iwxxm:surfaceWind>
      <iwxxm:runwayState>
        <iwxxm:AerodromeRunwayState allRunways="true">
          <iwxxm:depositType xlink:href="http://codes.wmo.int/bufr4/codeflag/0-20-086/0"/>
          <iwxxm:contamination xlink:href="http://codes.wmo.int/bufr4/codeflag/0-20-087/9"/>
          <iwxxm:depthOfDeposit uom="N/A" xsi:nil="true" nilReason="http://codes.wmo.int/common/nil/nothingOfOperationalSignificance"/>
          <iwxxm:estimatedSurfaceFrictionOrBrakingAction xlink:href="http://codes.wmo.int/bufr4/codeflag/0-20-089/95"/>
        </iwxxm:AerodromeRunwayState>
      </iwxxm:runwayState>
    </iwxxm:MeteorologicalAerodromeObservation>
  </iwxxm:observation>
</iwxxm:SPECI>
